README.md
setup.py
autosql/__init__.py
autosql/autosql.py
autosql/errors.py
autosql.egg-info/PKG-INFO
autosql.egg-info/SOURCES.txt
autosql.egg-info/dependency_links.txt
autosql.egg-info/top_level.txt