Metadata-Version: 2.1
Name: autosql
Version: 1.0.0
Summary: UNKNOWN
Home-page: https://github.com/YEZIHANGISM/autosql
Author: yezihangism
Author-email: yezihangism@gmail.com
License: UNKNOWN
Platform: UNKNOWN
